buzx/__init__.py
buzx/__main__.py
buzx/downloader.py
buzx-1.2.1.dist-info/METADATA
buzx-1.2.1.dist-info/WHEEL
buzx-1.2.1.dist-info/entry_points.txt
buzx-1.2.1.dist-info/top_level.txt
buzx-1.2.1.dist-info/RECORD
