Metadata-Version: 2.1
Name: buzx
Version: 1.2.1
Requires-Python: >=3.6
Requires-Dist: requests
Requires-Dist: tqdm
